sarmat/__init__.py
sarmat/core/__init__.py
sarmat/core/constants/__init__.py
sarmat/core/constants/exception_constants.py
sarmat/core/constants/formats.py
sarmat/core/constants/sarmat_constants.py
sarmat/core/context/__init__.py
sarmat/core/context/models/__init__.py
sarmat/core/context/models/dispatcher_models.py
sarmat/core/context/models/geo_models.py
sarmat/core/context/models/sarmat_models.py
sarmat/core/context/models/traffic_management_models.py
sarmat/core/context/models/vehicle_models.py
sarmat/core/context/tools/__init__.py
sarmat/core/context/tools/calculators/__init__.py
sarmat/core/context/tools/calculators/const.py
sarmat/core/context/tools/calculators/duration.py
sarmat/core/context/tools/calculators/metrics.py
sarmat/core/context/tools/calculators/price.py
sarmat/core/context/tools/routemaster_tools.py
sarmat-4.5.2.dist-info/LICENSE
sarmat-4.5.2.dist-info/METADATA
sarmat-4.5.2.dist-info/WHEEL
sarmat-4.5.2.dist-info/RECORD
