Metadata-Version: 2.3
Name: sarmat
Version: 4.5.2
Summary: Sarmat package for IT decisions in the passenger transport sphere
License: MIT
Author: jn
Author-email: artel61@gmail.com
Requires-Python: >=3.11,<4.0
Classifier: License :: OSI Approved :: MIT License
Classifier: Operating System :: OS Independent
Classifier: Programming Language :: Python :: 3
Classifier: Programming Language :: Python :: 3.11
Classifier: Programming Language :: Python :: 3.12
Classifier: Programming Language :: Python :: 3.13
Requires-Dist: flake8 (>=7.2.0,<8.0.0)
Requires-Dist: mypy (>=1.15.0,<2.0.0)
Requires-Dist: twine (>=6.1.0,<7.0.0)
